tree_sitter_formatter/__about__.py
tree_sitter_formatter/__init__.py
tree_sitter_formatter/cli.py
tree_sitter_formatter/default_tree_sitter_formatter.toml
tree_sitter_formatter/formatter.py
tree_sitter_formatter/standard_config.py
tree_sitter_formatter-0.1.0.dev2.dist-info/METADATA
tree_sitter_formatter-0.1.0.dev2.dist-info/WHEEL
tree_sitter_formatter-0.1.0.dev2.dist-info/entry_points.txt
tree_sitter_formatter-0.1.0.dev2.dist-info/licenses/LICENSE
tree_sitter_formatter-0.1.0.dev2.dist-info/RECORD
