Metadata-Version: 2.1
Name: tree-sitter-formatter
Version: 0.1.0.dev2
Summary: A simple markdown formatter
Project-URL: Source, https://github.com/waylonwalker/tree-sitter-formatter
Author-email: Waylon Walker <waylon@waylonwalker.com>
License: Copyright (c) 2012-2022 Waylon Walker
License-File: LICENSE
Classifier: Development Status :: 3 - Alpha
Classifier: Environment :: Console
Classifier: Intended Audience :: Developers
Classifier: Natural Language :: English
Classifier: Operating System :: OS Independent
Classifier: Programming Language :: Python
Classifier: Programming Language :: Python :: 3
Classifier: Programming Language :: Python :: 3 :: Only
Classifier: Programming Language :: Python :: 3.6
Classifier: Programming Language :: Python :: 3.7
Classifier: Programming Language :: Python :: 3.8
Classifier: Programming Language :: Python :: 3.9
Classifier: Programming Language :: Python :: 3.10
Classifier: Programming Language :: Python :: Implementation :: CPython
Classifier: Programming Language :: Python :: Implementation :: PyPy
Classifier: Topic :: Software Development
Classifier: Topic :: Text Processing
Classifier: Typing :: Typed
Requires-Python: >=3.6
Requires-Dist: anyconfig
Requires-Dist: ipdb
Requires-Dist: rich
Requires-Dist: tree-sitter-languages
Requires-Dist: typer
